MANIFEST.in
README.md
setup.cfg
setup.py
configuration/__init__.py
configuration/config.yaml
configuration/logging_config.yaml
employee_insights.egg-info/PKG-INFO
employee_insights.egg-info/SOURCES.txt
employee_insights.egg-info/dependency_links.txt
employee_insights.egg-info/requires.txt
employee_insights.egg-info/top_level.txt
src/__init__.py
src/employee_details.py
tests/__init__.py
tests/test_avg_salary.py
tests/test_fltrEmp.py
tests/test_save_avg_to_file.py
tests/test_save_data_to_file.py