Metadata-Version: 2.1
Name: employee_insights
Version: 1.0.0
Summary: This package is used to get the employee details like employees whose date_of_joining is greater than input date_of_joining and average salary of empolyees of a particular designation.
Author: Simran
Author-email: simran.saxena@dataverze.ai
Classifier: Programming Language :: Python :: 3
Requires-Dist: black==24.3.0
Requires-Dist: pytest==8.0.2
Requires-Dist: setuptools==69.1.1
Requires-Dist: wheel==0.42.0
Requires-Dist: twine==5.0.0
Requires-Dist: pre-commit==3.6.2
Requires-Dist: mysql-connector-python==8.3.0
Requires-Dist: pandas==2.2.1
Requires-Dist: pandasql==0.7.3
